cli/__init__.py
cli/cli.py
cli/generate.py
cli/init.py
cli/manifest.schema.json
cli/update.py
cli/utils.py
cli/templates/cookiecutter.json
cli/templates/apps/mleap/cookiecutter.json
cli/templates/apps/mleap/{{cookiecutter.PROJECT_NAME_SLUG}}/README.rst
cli/templates/apps/mleap/{{cookiecutter.PROJECT_NAME_SLUG}}/mleap_model/.dockerignore
cli/templates/apps/mleap/{{cookiecutter.PROJECT_NAME_SLUG}}/mleap_model/Dockerfile
cli/templates/apps/mleap/{{cookiecutter.PROJECT_NAME_SLUG}}/mleap_model/Makefile
cli/templates/apps/mleap/{{cookiecutter.PROJECT_NAME_SLUG}}/mleap_model/requirements.txt
cli/templates/apps/mleap/{{cookiecutter.PROJECT_NAME_SLUG}}/mleap_model/databricks/SMSSpamCollection.tsv
cli/templates/apps/mleap/{{cookiecutter.PROJECT_NAME_SLUG}}/mleap_model/databricks/azuredeploy.json
cli/templates/apps/mleap/{{cookiecutter.PROJECT_NAME_SLUG}}/mleap_model/databricks/azuredeploy.parameters.json
cli/templates/apps/mleap/{{cookiecutter.PROJECT_NAME_SLUG}}/mleap_model/databricks/configure_databricks.sh
cli/templates/apps/mleap/{{cookiecutter.PROJECT_NAME_SLUG}}/mleap_model/databricks/create_secrets.sh
cli/templates/apps/mleap/{{cookiecutter.PROJECT_NAME_SLUG}}/mleap_model/databricks/deploy_resources.sh
cli/templates/apps/mleap/{{cookiecutter.PROJECT_NAME_SLUG}}/mleap_model/databricks/config/cluster.config.json
cli/templates/apps/mleap/{{cookiecutter.PROJECT_NAME_SLUG}}/mleap_model/databricks/config/run.mountblob.config.json
cli/templates/apps/mleap/{{cookiecutter.PROJECT_NAME_SLUG}}/mleap_model/databricks/notebooks/01_mount_blobstorage.py
cli/templates/apps/mleap/{{cookiecutter.PROJECT_NAME_SLUG}}/mleap_model/databricks/notebooks/02_train_model.scala
cli/templates/apps/mleap/{{cookiecutter.PROJECT_NAME_SLUG}}/mleap_model/databricks/notebooks/03_reload_mleap_model.scala
cli/templates/apps/mleap/{{cookiecutter.PROJECT_NAME_SLUG}}/mleap_model/trainer/.gitignore
cli/templates/apps/mleap/{{cookiecutter.PROJECT_NAME_SLUG}}/mleap_model/trainer/build.sbt
agogosml_cli-0.1.2.dist-info/METADATA
agogosml_cli-0.1.2.dist-info/WHEEL
agogosml_cli-0.1.2.dist-info/entry_points.txt
agogosml_cli-0.1.2.dist-info/top_level.txt
agogosml_cli-0.1.2.dist-info/RECORD
