Metadata-Version: 2.1
Name: agogosml-cli
Version: 0.1.2
Summary: Agogosml cli project to scaffold and generate an agogosml project.
Home-page: https://github.com/Microsoft/agogosml/agogosml_cli
Author: Rami Sayar
Author-email: rami.sayar@microsoft.com
License: MIT license
Keywords: agogosml_cli
Platform: UNKNOWN
Classifier: Development Status :: 2 - Pre-Alpha
Classifier: Intended Audience :: Developers
Classifier: License :: OSI Approved :: MIT License
Classifier: Natural Language :: English
Classifier: Programming Language :: Python :: 2
Classifier: Programming Language :: Python :: 2.7
Classifier: Programming Language :: Python :: 3
Classifier: Programming Language :: Python :: 3.4
Classifier: Programming Language :: Python :: 3.5
Classifier: Programming Language :: Python :: 3.6
Requires-Dist: jsonschema (==2.6.0)
Requires-Dist: Click (>=7.0)
Requires-Dist: jsonnet (==0.11.2)
Requires-Dist: validators (==0.12.3)
Requires-Dist: cookiecutter (==1.6.0)
Requires-Dist: git-url-parse (==1.1.0)
